HISTORY.rst
MANIFEST.in
README.md
requirements.txt
setup.cfg
setup.py
src/nameko_hot_reload/__init__.py
src/nameko_hot_reload/__main__.py
src/nameko_hot_reload/autoreload.py
src/nameko_hot_reload/cli_commands.py
src/nameko_hot_reload.egg-info/PKG-INFO
src/nameko_hot_reload.egg-info/SOURCES.txt
src/nameko_hot_reload.egg-info/dependency_links.txt
src/nameko_hot_reload.egg-info/entry_points.txt
src/nameko_hot_reload.egg-info/not-zip-safe
src/nameko_hot_reload.egg-info/requires.txt
src/nameko_hot_reload.egg-info/top_level.txt
src/nameko_hot_reload/cli/__init__.py
src/nameko_hot_reload/cli/main.py
src/nameko_hot_reload/cli/run.py