Metadata-Version: 1.2
Name: nameko-hot-reload
Version: 0.2.dev0
Summary: Nameko run with autoloading, logging file CLI option
Home-page: UNKNOWN
Author: Joey.Jiang
Author-email: joeeey9303@gmail.com
Maintainer: Joey.Jiang
Maintainer-email: joeeey9303@gmail.com
License: Apache License 2.0
Platform: UNKNOWN
Classifier: Intended Audience :: Developers
Classifier: Operating System :: OS Independent
Classifier: Programming Language :: Python
Classifier: Programming Language :: Python :: 2.7
Classifier: Programming Language :: Python :: 3
Classifier: Programming Language :: Python :: 3.2
Classifier: Programming Language :: Python :: 3.3
Classifier: Programming Language :: Python :: 3.4
Classifier: Programming Language :: Python :: 3.5
Classifier: Programming Language :: Python :: 3.6
Classifier: Topic :: Internet :: WWW/HTTP
